meshjp/__init__.py
meshjp/meshjp.py
tests/__init__.py
tests/test_meshjp.py
meshjp-0.1.0.dev0.dist-info/LICENSE
meshjp-0.1.0.dev0.dist-info/METADATA
meshjp-0.1.0.dev0.dist-info/WHEEL
meshjp-0.1.0.dev0.dist-info/top_level.txt
meshjp-0.1.0.dev0.dist-info/RECORD
